llm_only/__init__.py
llm_only/detector.py
llm_only/fastapi_middleware.py
llm_only/flask_decorator.py
llm_only-0.1.0.dist-info/licenses/LICENSE
llm_only-0.1.0.dist-info/METADATA
llm_only-0.1.0.dist-info/WHEEL
llm_only-0.1.0.dist-info/top_level.txt
llm_only-0.1.0.dist-info/RECORD
