Metadata-Version: 2.4
Name: llm-only
Version: 0.1.0
Summary: Conditionally serve content to LLM crawlers in Python web frameworks.
Author-email: Amal Alexander <amalalex95@gmail.com>
License: MIT
Requires-Python: >=3.8
License-File: LICENSE
Requires-Dist: fastapi
Requires-Dist: starlette
Requires-Dist: flask
Dynamic: license-file
